byted_overpass_flow_flow_platform_management_api/__init__.py
byted_overpass_flow_flow_platform_management_api-0.0.1.dist-info/METADATA
byted_overpass_flow_flow_platform_management_api-0.0.1.dist-info/WHEEL
byted_overpass_flow_flow_platform_management_api-0.0.1.dist-info/top_level.txt
byted_overpass_flow_flow_platform_management_api-0.0.1.dist-info/RECORD
